tradingview_ws/__init__.py
tradingview_ws/__version__.py
tradingview_ws/tdws.py
tradingview_ws-0.0.3.dist-info/LICENSE
tradingview_ws-0.0.3.dist-info/METADATA
tradingview_ws-0.0.3.dist-info/WHEEL
tradingview_ws-0.0.3.dist-info/top_level.txt
tradingview_ws-0.0.3.dist-info/RECORD
